serpapi_client/__init__.py
serpapi_client/exception.py
serpapi_client/fix.py
serpapi_client/google/__init__.py
serpapi_client/google/client.py
serpapi_client-2024.7.2.dist-info/METADATA
serpapi_client-2024.7.2.dist-info/WHEEL
serpapi_client-2024.7.2.dist-info/entry_points.txt
serpapi_client-2024.7.2.dist-info/top_level.txt
serpapi_client-2024.7.2.dist-info/RECORD
