Metadata-Version: 2.1
Name: serpapi_client
Version: 2024.7.2
Author: Woojin Cho
Author-email: woojin.cho@gmail.com
License: MIT License
Requires-Python: >=3.9
Requires-Dist: aiohttp
Requires-Dist: aiolimiter
Requires-Dist: click
